sam_alignment_reconstructor/__init__.py
sam_alignment_reconstructor/cli.py
sam_alignment_reconstructor/pairwise.py
sam_alignment_reconstructor-0.0.5.dist-info/METADATA
sam_alignment_reconstructor-0.0.5.dist-info/RECORD
sam_alignment_reconstructor-0.0.5.dist-info/WHEEL
sam_alignment_reconstructor-0.0.5.dist-info/entry_points.txt
sam_alignment_reconstructor-0.0.5.dist-info/top_level.txt
