Metadata-Version: 2.1
Name: sam-alignment-reconstructor
Version: 0.0.5
Summary: SAM Alignment Reconstructor
Home-page: https://github.com/lairdm/sam-alignment-reconstructor.git
Author: Matthew Laird
Author-email: lairdm@ebi.ac.uk
License: Apache 2.0
Keywords: sam alignment bioinformatics
Platform: UNKNOWN
Classifier: Development Status :: 4 - Beta
Classifier: Intended Audience :: Developers
Classifier: License :: OSI Approved :: Apache Software License
Classifier: Programming Language :: Python :: 2
Classifier: Programming Language :: Python :: 2.7
Classifier: Programming Language :: Python :: 3
Classifier: Programming Language :: Python :: 3.4
Classifier: Programming Language :: Python :: 3.5
Classifier: Programming Language :: Python :: 3.6
Classifier: Programming Language :: Python :: 3.7
Requires-Python: >=2.7, !=3.0.*, !=3.1.*, !=3.2.*, !=3.3.*, <4
Provides-Extra: dev
Provides-Extra: docs
Provides-Extra: lint
Provides-Extra: test
Requires-Dist: click (==6.7)
Requires-Dist: simplesam (==0.1.2)
Requires-Dist: six (==1.11.0)
Requires-Dist: future (>=0.16.0)
Provides-Extra: dev
Requires-Dist: tox; extra == 'dev'
Provides-Extra: docs
Requires-Dist: sphinx (>=1.7.5); extra == 'docs'
Requires-Dist: sphinxcontrib-fulltoc; extra == 'docs'
Requires-Dist: tox; extra == 'docs'
Provides-Extra: lint
Requires-Dist: pylint; extra == 'lint'
Requires-Dist: tox; extra == 'lint'
Provides-Extra: test
Requires-Dist: pytest; extra == 'test'
Requires-Dist: pytest-cov; extra == 'test'
Requires-Dist: tox; extra == 'test'
